{
  "faq_id": 2129689670173640493,
  "language": 0,
  "version": 3,
  "content": "When contacting Steam Support about a damaged or unreadable Steam Wallet code it is extremely important to provide us with a clear photo or scan of the entire back side of the Steam Wallet card. Please do not edit or mark the card.\n\nBelow are the two examples of how Wallet codes should be submitted to Steam Support:\n\n[img]https://support.steampowered.com/images/faq/wallet/epaywalletcard.png[/img] [img]https://support.steampowered.com/images/faq/wallet/fastcardwalletcard.png[/img]\n\n",
  "title": "How to Send Wallet Codes For Steam Support",
  "timestamp": "2021-07-10T19:49:55+00:00"
}